Metadata-Version: 2.1
Name: spokenTowritten
Version: 1.1
Summary: Library For Spoken to written
Home-page: https://github.com/Raman-Raje/spokenTowritten
Author: Raman Shinde
Author-email: raman.shinde15@gmail.com
License: MIT
Download-URL: https://github.com/Raman-Raje/spokenTowritten/archive/v_1.1.tar.gz
Platform: UNKNOWN
Classifier: Development Status :: 3 - Alpha
Classifier: Intended Audience :: Developers
Classifier: Topic :: Software Development :: Build Tools
Classifier: License :: OSI Approved :: MIT License
Classifier: Programming Language :: Python :: 3
Classifier: Programming Language :: Python :: 3.4
Classifier: Programming Language :: Python :: 3.5
Classifier: Programming Language :: Python :: 3.6
